ocr_utils/__init__.py
ocr_utils-0.1.dist-info/METADATA
ocr_utils-0.1.dist-info/WHEEL
ocr_utils-0.1.dist-info/top_level.txt
ocr_utils-0.1.dist-info/RECORD
