Metadata-Version: 2.1
Name: ocr-utils
Version: 0.1
Summary: debug OCR utils
Home-page: http://github.com/storborg/funniest
Author: Danh Vo
Author-email: vothanhdanh9526@gmail.com
License: MIT
Platform: UNKNOWN
